discordDBPlus/__init__.py
discordDBPlus/db.py
discordDBPlus/models/__init__.py
discordDBPlus/models/errors.py
discordDBPlus/models/types.py
DiscordDBPlus-0.0.9.dist-info/LICENSE
DiscordDBPlus-0.0.9.dist-info/METADATA
DiscordDBPlus-0.0.9.dist-info/WHEEL
DiscordDBPlus-0.0.9.dist-info/top_level.txt
DiscordDBPlus-0.0.9.dist-info/RECORD
