Metadata-Version: 2.1
Name: DiscordDBPlus
Version: 0.0.9
Summary: A simple database which uses a Discord channel to store data.
Home-page: https://github.com/AtaeKurri/DiscordDBPlus
Author: AtaeKurri
License: MIT
Platform: UNKNOWN
Classifier: Development Status :: 5 - Production/Stable
Classifier: License :: OSI Approved :: MIT License
Classifier: Intended Audience :: Developers
Classifier: Natural Language :: English
Classifier: Operating System :: OS Independent
Classifier: Programming Language :: Python :: 3.6
Classifier: Programming Language :: Python :: 3.7
Classifier: Topic :: Internet
Classifier: Topic :: Utilities
Requires-Dist: discord.py
